markdown_to_respec.py
markdown_to_respec-0.4.1.dist-info/METADATA
markdown_to_respec-0.4.1.dist-info/WHEEL
markdown_to_respec-0.4.1.dist-info/entry_points.txt
markdown_to_respec-0.4.1.dist-info/top_level.txt
markdown_to_respec-0.4.1.dist-info/RECORD
