Metadata-Version: 2.1
Name: markdown-to-respec
Version: 0.4.1
Summary: Convert specifications written in Markdown to ReSpec HTML
Home-page: https://github.com/webrecorder/markdown-to-respec
Author: Ed Summers
Author-email: info@webrecorder.net
License: Apache 2.0
Requires-Dist: python-frontmatter
Requires-Dist: GitPython
